pdf2htmldir.py
pdf2htmldir-0.3.0.dist-info/entry_points.txt
pdf2htmldir-0.3.0.dist-info/LICENSE
pdf2htmldir-0.3.0.dist-info/WHEEL
pdf2htmldir-0.3.0.dist-info/METADATA
pdf2htmldir-0.3.0.dist-info/RECORD
