Metadata-Version: 2.1
Name: pdf2htmldir
Version: 0.3.0
Summary: convert pdf to html
Author-email: nhannht <nhanclassroom@gmail.com>
Classifier: License :: OSI Approved :: MIT License
